django_stripe/__init__.py
django_stripe/admin.py
django_stripe/apps.py
django_stripe/db/__init__.py
django_stripe/db/fields.py
django_stripe/migrations/0001_initial.py
django_stripe/migrations/__init__.py
django_stripe/models/__init__.py
django_stripe/models/base.py
django_stripe/models/webhook_event.py
django_stripe/settings.py
django_stripe/urls.py
django_stripe/utils/__init__.py
django_stripe/utils/request.py
django_stripe/webhook_view.py
django_stripe/webhooks.py
django_stripe_lite-0.8.0.dist-info/METADATA
django_stripe_lite-0.8.0.dist-info/WHEEL
django_stripe_lite-0.8.0.dist-info/RECORD
